<?xml version="1.0" encoding="UTF-8"?>
<?xml-stylesheet href="vehiculos.xslt" type="text/xsl"?>

<vehiculos>
    <vehiculo>
        <marca>Ferrari</marca>
        <web>https://www.ferrari.com</web>
        <modelo año="2024">F6 Spider</modelo>
        <precio>262.000€</precio>
    </vehiculo>
    <vehiculo>
        <marca>Lamborghini</marca>
        <web>https://www.lamborghini.com/es-en</web>
        <modelo año="2023">Lamborghini Urus</modelo>
        <precio>232.715€</precio>
    </vehiculo>
    <vehiculo>
        <marca>Bugatti</marca>
        <web>https://www.bugatti.com</web>
        <modelo año="2024">Chiron</modelo>
        <precio>2.500.000€</precio>
    </vehiculo>
    <vehiculo>
        <marca>Rolls-Royce</marca>
        <web>https://www.rolls-roycemotorcars.com</web>
        <modelo año="2022">Phantom</modelo>
        <precio>475.000€</precio>
    </vehiculo>
    <vehiculo>
        <marca>McLaren</marca>
        <web>https://cars.mclaren.com</web>
        <modelo año="2023">720S</modelo>
        <precio>310.500€</precio>
    </vehiculo>
    <vehiculo>
        <marca>Porsche</marca>
        <web>https://www.porsche.com</web>
        <modelo año="2024">911 Turbo S</modelo>
        <precio>252.500€</precio>
    </vehiculo>
    <vehiculo>
        <marca>Koenigsegg</marca>
        <web>https://www.koenigsegg.com</web>
        <modelo año="2025">Jesko</modelo>
        <precio>3.000.000€</precio>
    </vehiculo>
    <vehiculo>
        <marca>Aston Martin</marca>
        <web>https://www.astonmartin.com</web>
        <modelo año="2023">DBS Superleggera</modelo>
        <precio>295.500€</precio>
    </vehiculo>
    <vehiculo>
        <marca>Bentley</marca>
        <web>https://www.bentleymotors.com</web>
        <modelo año="2022">Continental GT</modelo>
        <precio>230.000€</precio>
    </vehiculo>
    <vehiculo>
        <marca>Maserati</marca>
        <web>https://www.maserati.com</web>
        <modelo año="2024">MC20</modelo>
        <precio>250.000€</precio>
    </vehiculo>
    <vehiculo>
        <marca>Pagani</marca>
        <web>https://www.pagani.com</web>
        <modelo año="2025">Huayra</modelo>
        <precio>2.600.000€</precio>
    </vehiculo>
    <vehiculo>
        <marca>Mercedes-Benz</marca>
        <web>https://www.mercedes-benz.com</web>
        <modelo año="2023">AMG GT Black Series</modelo>
        <precio>335.000€</precio>
    </vehiculo>
</vehiculos>
